SummitVentureStudioMarketAnalyzer/ChatGPTApi.py
SummitVentureStudioMarketAnalyzer/GovGrantsAPI.py
SummitVentureStudioMarketAnalyzer/PatentAPI.py
SummitVentureStudioMarketAnalyzer/PitchBookAPI.py
SummitVentureStudioMarketAnalyzer/__init__.py
src/ChatGPTApi.py
src/GovGrantsAPI.py
src/PatentAPI.py
src/PitchBookAPI.py
src/__init__.py
SummitVentureStudioMarketAnalyzer-1.0.14.dist-info/METADATA
SummitVentureStudioMarketAnalyzer-1.0.14.dist-info/WHEEL
SummitVentureStudioMarketAnalyzer-1.0.14.dist-info/top_level.txt
SummitVentureStudioMarketAnalyzer-1.0.14.dist-info/RECORD
