Metadata-Version: 2.1
Name: SummitVentureStudioMarketAnalyzer
Version: 1.0.14
Author: willem@wrench.ai
Requires-Dist: wrenchcl >=1.3.5
Requires-Dist: pandas >=2.1.0
Requires-Dist: requests >=2.31.0
Requires-Dist: python-dotenv ~=1.0.0
Requires-Dist: tenacity ~=8.2.3
